setup.cfg
setup.py
pyOSCapi/__init__.py
pyOSCapi/oscapi.py
pyOSCapi.egg-info/PKG-INFO
pyOSCapi.egg-info/SOURCES.txt
pyOSCapi.egg-info/dependency_links.txt
pyOSCapi.egg-info/requires.txt
pyOSCapi.egg-info/top_level.txt