Metadata-Version: 1.1
Name: pyOSCapi
Version: 0.2
Summary: Python API to interact with network devices using the Open Spherical Camera API
Home-page: https://github.com/florianl/pyOSCapi/
Author: Florian Lehner
Author-email: dev@der-flo.net
License: Apache License 2.0
Download-URL: https://github.com/florianl/pyOSCapi/archive/master.tar.gz
Keywords: Open Spherical Camera,API 
Platform: UNKNOWN
Classifier: Development Status :: 4 - Beta
Classifier: Intended Audience :: Developers
